hass_frontend/__init__.py
hass_frontend/authorize.html
hass_frontend/index.html
hass_frontend/onboarding.html
hass_frontend/robots.txt
hass_frontend/service_worker.js
hass_frontend/frontend_latest/0.chunk.js
hass_frontend/frontend_latest/1.chunk.js
hass_frontend/frontend_latest/10.chunk.js
hass_frontend/frontend_latest/11.chunk.js
hass_frontend/frontend_latest/12.chunk.js
hass_frontend/frontend_latest/13.chunk.js
hass_frontend/frontend_latest/14.chunk.js
hass_frontend/frontend_latest/15.chunk.js
hass_frontend/frontend_latest/16.chunk.js
hass_frontend/frontend_latest/17.chunk.js
hass_frontend/frontend_latest/18.chunk.js
hass_frontend/frontend_latest/19.chunk.js
hass_frontend/frontend_latest/2.chunk.js
hass_frontend/frontend_latest/20.chunk.js
hass_frontend/frontend_latest/21.chunk.js
hass_frontend/frontend_latest/22.chunk.js
hass_frontend/frontend_latest/23.chunk.js
hass_frontend/frontend_latest/24.chunk.js
hass_frontend/frontend_latest/25.chunk.js
hass_frontend/frontend_latest/26.chunk.js
hass_frontend/frontend_latest/27.chunk.js
hass_frontend/frontend_latest/28.chunk.js
hass_frontend/frontend_latest/29.chunk.js
hass_frontend/frontend_latest/3.chunk.js
hass_frontend/frontend_latest/30.chunk.js
hass_frontend/frontend_latest/31.chunk.js
hass_frontend/frontend_latest/32.chunk.js
hass_frontend/frontend_latest/33.chunk.js
hass_frontend/frontend_latest/34.chunk.js
hass_frontend/frontend_latest/35.chunk.js
hass_frontend/frontend_latest/36.chunk.js
hass_frontend/frontend_latest/37.chunk.js
hass_frontend/frontend_latest/38.chunk.js
hass_frontend/frontend_latest/39.chunk.js
hass_frontend/frontend_latest/393b925a75277824ba3f.worker.js
hass_frontend/frontend_latest/4.chunk.js
hass_frontend/frontend_latest/40.chunk.js
hass_frontend/frontend_latest/41.chunk.js
hass_frontend/frontend_latest/42.chunk.js
hass_frontend/frontend_latest/43.chunk.js
hass_frontend/frontend_latest/44.chunk.js
hass_frontend/frontend_latest/45.chunk.js
hass_frontend/frontend_latest/46.chunk.js
hass_home_assistant_frontend-20200427.2.dist-info/LICENSE.md
hass_home_assistant_frontend-20200427.2.dist-info/METADATA
hass_home_assistant_frontend-20200427.2.dist-info/WHEEL
hass_home_assistant_frontend-20200427.2.dist-info/top_level.txt
hass_home_assistant_frontend-20200427.2.dist-info/RECORD
