Metadata-Version: 2.1
Name: hass-home-assistant-frontend
Version: 20200427.2
Summary: The HaaS version of Home Assistant frontend
Home-page: https://gitlab.svccomp.de/svccomp-students/entwicklungsprojekt/2020/haas-human-as-a-sensor/home-assistant-frontend
Author: The HaaS Project and Home Assistant Authors
Author-email: author@email.com
License: Apache License 2.0
Platform: UNKNOWN
